bestapi/__init__.py
bestapi/concurrency.py
bestapi/responses.py
bestapi/types.py
bestapi-0.1.0.dist-info/METADATA
bestapi-0.1.0.dist-info/WHEEL
bestapi-0.1.0.dist-info/RECORD
