Metadata-Version: 2.3
Name: bestapi
Version: 0.1.0
Summary: I'm just trying to make my life easier! 🤷‍♂️
Author-email: Marcelo Trylesinski <marcelotryle@gmail.com>
Requires-Python: >=3.9
Requires-Dist: starlette>=0.37.2
